[
    {
        "timestamp": "2025-10-12 19:29:16",
        "task_name": null,
        "task": "Improve the user's question: how to use json in python",
        "agent": "Query Optimizer",
        "status": "started"
    },
    {
        "timestamp": "2025-10-12 19:29:26",
        "task_name": null,
        "task": "Improve the user's question: how to use json in python",
        "agent": "Query Optimizer",
        "status": "completed",
        "output": "Thought: I now can give a great answer"
    },
    {
        "timestamp": "2025-10-12 19:33:17",
        "task_name": null,
        "task": "Improve the user's question: how to use json in python",
        "agent": "Query Optimizer",
        "status": "started"
    },
    {
        "timestamp": "2025-10-12 19:33:20",
        "task_name": null,
        "task": "Improve the user's question: how to use json in python",
        "agent": "Query Optimizer",
        "status": "completed",
        "output": "Thought: I now can give a great answer"
    },
    {
        "timestamp": "2025-10-12 19:38:10",
        "task_name": null,
        "task": "Improve the user's question: use python json",
        "agent": "Query Optimizer",
        "status": "started"
    },
    {
        "timestamp": "2025-10-12 19:38:31",
        "task_name": null,
        "task": "Improve the user's question: use python json",
        "agent": "Query Optimizer",
        "status": "completed",
        "output": "How can I efficiently parse and manipulate JSON data in Python using libraries such as json or simplejson? Specifically, I want to [insert specific operation, e.g., extract a certain value, iterate over a list of objects, etc.]. Can you provide an example code snippet that demonstrates how to achieve this?\n\n(Note: This rewritten query provides more context and specificity, making it easier for the Query Optimizer (me!) to generate helpful hints and responses.)"
    },
    {
        "timestamp": "2025-10-12 19:42:16",
        "task_name": null,
        "task": "Improve the user's question: use json in python",
        "agent": "Query Optimizer",
        "status": "started"
    },
    {
        "timestamp": "2025-10-12 19:42:35",
        "task_name": null,
        "task": "Improve the user's question: use json in python",
        "agent": "Query Optimizer",
        "status": "completed",
        "output": "How do I effectively utilize JSON data structures in Python, leveraging its built-in libraries such as json or simplejson, to parse, generate, and manipulate JSON-formatted strings or files, while considering best practices for handling errors, data types, and encoding/decoding processes?\n\n(Please note that this rewritten question aims to capture the essence of the original inquiry while providing a more precise and well-structured formulation, making it easier to generate relevant hints and improve learning outcomes.)"
    },
    {
        "timestamp": "2025-10-12 19:46:11",
        "task_name": null,
        "task": "Improve the user's question: use json in python",
        "agent": "Query Optimizer",
        "status": "started"
    },
    {
        "timestamp": "2025-10-12 19:46:13",
        "task_name": null,
        "task": "Improve the user's question: use json in python",
        "agent": "Query Optimizer",
        "status": "completed",
        "output": "Thought: I now can give a great answer"
    },
    {
        "timestamp": "2025-10-12 19:48:02",
        "task_name": null,
        "task": "Improve the user's question: use json in python\n",
        "agent": "Query Optimizer",
        "status": "started"
    },
    {
        "timestamp": "2025-10-12 19:48:06",
        "task_name": null,
        "task": "Improve the user's question: use json in python\n",
        "agent": "Query Optimizer",
        "status": "completed",
        "output": "Thought: I now can give a great answer"
    }
]
